examples/__init__.py
examples/google_search.py
yasirapi/__init__.py
yasirapi/yasirapi.py
yasirpedia_api-0.0.6.dist-info/LICENSE
yasirpedia_api-0.0.6.dist-info/METADATA
yasirpedia_api-0.0.6.dist-info/WHEEL
yasirpedia_api-0.0.6.dist-info/top_level.txt
yasirpedia_api-0.0.6.dist-info/RECORD
