Metadata-Version: 2.1
Name: yasirpedia-api
Version: 0.0.6
Summary: Official Python Wrapper for YasirPedia API.
Home-page: https://github.com/yasirarism/YasirPediaApi-Py
Author: Yasir Aris M
Author-email: mail@yasir.eu.org
License: License :: OSI Approved :: GNU Lesser General Public License v3 (LGPLv3)
Classifier: Programming Language :: Python :: 3
Classifier: Programming Language :: Python :: 3.6
Classifier: Programming Language :: Python :: 3.7
Classifier: Programming Language :: Python :: 3.8
Classifier: Programming Language :: Python :: 3.9
Classifier: Operating System :: OS Independent
Requires-Python: >=3.6
License-File: LICENSE
Requires-Dist: requests
